{
  "XFAB": {
    "ticker": "XFAB",
    "name": "X-FAB",
    "exchange": "Euronext Paris / 需按实际交易代码确认",
    "sector": "特种晶圆代工",
    "business": "X-FAB 是欧洲特种晶圆代工公司，业务覆盖汽车、工业、医疗、通信和传感器等应用。Serenity 相关论点主要集中在硅光子、磷化铟集成、碳化硅和 AI 数据中心电源相关特种工艺能力。",
    "fundamentals": [
      "重点看高价值特种工艺收入占比，而不只是传统代工周期。",
      "关注毛利率、产能利用率、资本开支、订单能见度和汽车/工业周期。",
      "需要核验硅光子、InP、SiC 和 800V 电源半导体相关收入或客户验证进展。"
    ],
    "analystView": [
      "待接入欧洲券商覆盖和一致预期。",
      "分析师观点应重点拆分传统汽车/工业业务与 AI 光通信、硅光子主题贡献。",
      "需要确认市场是否已经把 AI/硅光子逻辑计入估值。"
    ],
    "risks": [
      "欧洲小盘流动性和信息披露频率低于美股大盘。",
      "社媒点名后短期涨幅可能放大估值风险。",
      "硅光子或 InP 逻辑兑现周期可能长于市场预期。"
    ],
    "quote": null,
    "priceTarget": null,
    "recommendation": null,
    "dataNotes": "当前行情适配器主要覆盖 Finnhub 美股数据；XFAB 属于欧洲市场，需要后续接入 Euronext、Yahoo Finance 欧洲代码、FactSet、Bloomberg 或其他欧洲行情源。"
  },
  "SIVE": {
    "ticker": "SIVE",
    "name": "Sivers Semiconductors",
    "exchange": "Nasdaq Stockholm / 需按实际交易代码确认",
    "sector": "光通信与射频半导体",
    "business": "Sivers Semiconductors 提供光子学和无线半导体方案。Serenity 相关论点主要集中在连续波激光器、外置激光源和共封装光学潜在瓶颈。",
    "fundamentals": [
      "重点看光子学业务订单、客户验证和收入兑现节奏。",
      "关注现金消耗、融资需求、毛利率和客户集中度。",
      "如果 CPO/ELS 放量晚于预期，收入和估值兑现可能延后。"
    ],
    "analystView": [
      "待接入北欧本地券商或专业科技研究覆盖。",
      "需要区分真实产业链验证与纯主题交易。",
      "分析师更新应重点关注客户认证、设计导入和量产时间表。"
    ],
    "risks": [
      "小盘高波动和流动性风险。",
      "客户认证周期长，订单转收入存在不确定性。",
      "融资或股权稀释风险。"
    ],
    "quote": null,
    "priceTarget": null,
    "recommendation": null,
    "dataNotes": "当前行情适配器主要覆盖 Finnhub 美股数据；SIVE 属于瑞典市场，需要后续接入 Nasdaq Nordic、Yahoo Finance 欧洲代码、FactSet、Bloomberg 或其他北欧行情源。"
  },
  "AXTI": {
    "ticker": "AXTI",
    "name": "AXT Inc.",
    "exchange": "NASDAQ",
    "sector": "化合物半导体衬底",
    "business": "生产化合物半导体衬底，包括磷化铟、砷化镓等。Serenity 相关论点集中在 AI 光通信上游 InP 衬底瓶颈。",
    "fundamentals": [
      "重点看 InP 业务收入、产能和价格。",
      "关注中国供应链、原材料和客户集中度。"
    ],
    "analystView": [
      "待接入一致预期和目标价。",
      "需要识别分析师是否把 AI 光通信 InP 瓶颈纳入模型。"
    ],
    "risks": [
      "周期性半导体需求。",
      "中美供应链和监管风险。",
      "小盘流动性和估值波动。"
    ],
    "quote": null,
    "priceTarget": null,
    "recommendation": null
  },
  "AAOI": {
    "ticker": "AAOI",
    "name": "Applied Optoelectronics",
    "exchange": "NASDAQ",
    "sector": "光模块 / 光通信",
    "business": "面向数据中心、有线电视和通信市场的光通信产品供应商。",
    "fundamentals": [
      "重点看数据中心收入增长、毛利率改善和大客户订单。",
      "关注产能扩张、库存和客户集中度。"
    ],
    "analystView": [
      "待接入一致预期。",
      "分析师观点应重点汇总收入上修、毛利率假设和订单能见度。"
    ],
    "risks": [
      "客户集中。",
      "光模块价格竞争。",
      "股价已大幅上涨后的风险收益比变化。"
    ],
    "quote": null,
    "priceTarget": null,
    "recommendation": null
  },
  "IREN": {
    "ticker": "IREN",
    "name": "IREN",
    "exchange": "NASDAQ",
    "sector": "比特币挖矿 / AI 数据中心",
    "business": "原以比特币挖矿和低成本电力基础设施为核心，市场也关注其向 AI 数据中心/算力基础设施转型的可能性。",
    "fundamentals": [
      "核心变量包括电力成本、算力规模、比特币价格和 AI 云业务转型进度。",
      "资本开支和融资方式会显著影响每股价值。"
    ],
    "analystView": [
      "待接入华尔街一致预期。",
      "分析师观点应拆成比特币挖矿价值、AI 数据中心价值和资本结构三部分。"
    ],
    "risks": [
      "大额 ATM 或股权融资稀释。",
      "比特币价格波动。",
      "AI 转型叙事兑现不确定。"
    ],
    "quote": null,
    "priceTarget": null,
    "recommendation": null
  },
  "XFAB": {
    "ticker": "XFAB",
    "name": "XFAB"
  },
  "SIVE": {
    "ticker": "SIVE",
    "name": "SIVE"
  }
}
